LICENSE
MANIFEST.in
README.md
setup.py
libpython.egg-info/PKG-INFO
libpython.egg-info/SOURCES.txt
libpython.egg-info/dependency_links.txt
libpython.egg-info/not-zip-safe
libpython.egg-info/requires.txt
libpython.egg-info/top_level.txt
libpythonpro/__init__.py
libpythonpro/github_api.py